mcp_rquest/__init__.py
mcp_rquest/__main__.py
mcp_rquest/server.py
mseep_mcp_rquest-0.1.17.dist-info/METADATA
mseep_mcp_rquest-0.1.17.dist-info/WHEEL
mseep_mcp_rquest-0.1.17.dist-info/entry_points.txt
mseep_mcp_rquest-0.1.17.dist-info/licenses/LICENSE.txt
mseep_mcp_rquest-0.1.17.dist-info/RECORD
